README.md
setup.py
src/controlversion/__init__.py
src/controlversion/controller.py
src/controlversion.egg-info/PKG-INFO
src/controlversion.egg-info/SOURCES.txt
src/controlversion.egg-info/dependency_links.txt
src/controlversion.egg-info/requires.txt
src/controlversion.egg-info/top_level.txt